{"P12": {"labels": ["CG"], "postTitle": "\u7978\u6d25\u795eCG", "postUrl": "post/huo-jin-shen-CG.html", "createdDate": "2024-07-10", "dateLabelColor": "#bc4c00"}, "P11": {"labels": ["maya"], "postTitle": "maya\u5c0f\u6280\u5de7\u4e00\u53cc\u51fb\u5de5\u5177\u67b6\u547d\u4ee4\u6253\u5f00\u547d\u4ee4\u9009\u9879\u7a97\u53e3", "postUrl": "post/maya-xiao-ji-qiao-yi-shuang-ji-gong-ju-jia-ming-ling-da-kai-ming-ling-xuan-xiang-chuang-kou.html", "createdDate": "2024-07-05", "dateLabelColor": "#bc4c00"}, "P1": {"labels": ["\u79d1\u6280"], "postTitle": "\u5c0f\u7231\u97f3\u7bb1pro\u63a5\u5165migpt\u540eAI\u5524\u9192\u4fdd\u59c6\u7ea7\u4f7f\u7528\u8bf4\u660e", "postUrl": "post/xiao-ai-yin-xiang-pro-jie-ru-migpt-hou-AI-huan-xing-bao-mu-ji-shi-yong-shuo-ming.html", "createdDate": "2024-06-30", "dateLabelColor": "#bc4c00"}, "P3": {"labels": ["CG"], "postTitle": "\u732b\u5dddCG", "postUrl": "post/mao-chuan-CG.html", "createdDate": "2024-06-11", "dateLabelColor": "#bc4c00"}, "P5": {"labels": ["CG"], "postTitle": "\u86cb\u4ed4\u6ed1\u6ed1", "postUrl": "post/dan-zi-hua-hua.html", "createdDate": "2024-06-02", "dateLabelColor": "#bc4c00"}, "P8": {"labels": ["CG"], "postTitle": "\u6697\u9ed1\u7834\u574f\u795e\u4e0d\u673d\u4ed9\u5251\u8054\u52a8", "postUrl": "post/an-hei-po-huai-shen-bu-xiu-xian-jian-lian-dong.html", "createdDate": "2024-04-17", "dateLabelColor": "#bc4c00"}, "P10": {"labels": ["CG"], "postTitle": "QQ9", "postUrl": "post/QQ9.html", "createdDate": "2023-12-21", "dateLabelColor": "#A333D0"}, "P2": {"labels": ["CG"], "postTitle": "\u8ffd\u6708\u795eCG ", "postUrl": "post/zhui-yue-shen-CG%20.html", "createdDate": "2023-01-10", "dateLabelColor": "#A333D0"}, "P9": {"labels": ["CG"], "postTitle": "\u6697\u9ed1\u7834\u574f\u795e\u4e0d\u673d\u75af\u738b\u534e\u670d", "postUrl": "post/an-hei-po-huai-shen-bu-xiu-feng-wang-hua-fu.html", "createdDate": "2022-12-16", "dateLabelColor": "#1f883d"}, "P4": {"labels": ["CG"], "postTitle": "\u539f\u795e\u751f\u65e5\u4f1a", "postUrl": "post/yuan-shen-sheng-ri-hui.html", "createdDate": "2022-09-25", "dateLabelColor": "#1f883d"}, "P6": {"labels": ["CG"], "postTitle": "\u54c8\u5229\u6ce2\u7279\u9b54\u6cd5\u89c9\u9192", "postUrl": "post/ha-li-bo-te-mo-fa-jue-xing.html", "createdDate": "2022-09-08", "dateLabelColor": "#1f883d"}, "P7": {"labels": ["CG"], "postTitle": "\u68a6\u5e7b\u897f\u6e38\u4e09\u7ef4", "postUrl": "post/meng-huan-xi-you-san-wei.html", "createdDate": "2021-12-31", "dateLabelColor": "#0969da"}, "labelColorDict": {"bug": "#d73a4a", "CG": "#008672", "duplicate": "#cfd3d7", "enhancement": "#a2eeef", "good first issue": "#7057ff", "invalid": "#e4e669", "maya": "#d876e3", "wontfix": "#ffffff", "\u63d2\u4ef6": "#0075ca", "\u79d1\u6280": "#4813EF"}}